themispy/__init__.py
themispy/project/__init__.py
themispy/project/utils.py
themispy/scrapy/__init__.py
themispy/scrapy/items.py
themispy/scrapy/pipelines.py
themispy/scrapy/readers.py
themispy/scrapy/spiders.py
themispy-0.2.7.dist-info/METADATA
themispy-0.2.7.dist-info/WHEEL
themispy-0.2.7.dist-info/top_level.txt
themispy-0.2.7.dist-info/RECORD
