Metadata-Version: 2.1
Name: themispy
Version: 0.2.7
Home-page: https://pypi.org/project/themispy/
Project-URL: Documentation, https://themispy.readthedocs.io/pt_BR/latest/
Project-URL: Source, https://github.com/joao-kitajima/themispy
Classifier: Development Status :: 3 - Alpha
Classifier: Intended Audience :: Developers
Classifier: Programming Language :: Python :: 3.8
Classifier: Operating System :: POSIX :: Linux
Classifier: Framework :: Scrapy
Classifier: Natural Language :: Portuguese (Brazilian)
Requires-Dist: azure-functions
Requires-Dist: azure-storage-blob
Requires-Dist: scrapy
Requires-Dist: pytz
